LICENSE
MANIFEST.in
README.md
setup.cfg
setup.py
rir_generator/__init__.py
rir_generator.egg-info/PKG-INFO
rir_generator.egg-info/SOURCES.txt
rir_generator.egg-info/dependency_links.txt
rir_generator.egg-info/not-zip-safe
rir_generator.egg-info/requires.txt
rir_generator.egg-info/top_level.txt
rir_generator/_rir/build.py
rir_generator/_rir/rir_generator_core.cpp
rir_generator/_rir/rir_generator_core.h