Metadata-Version: 2.1
Name: rir-generator
Version: 0.2.0
Summary: Room Impulse Response Generator.
Author: Nils Werner
Author-email: nils.werner@fau.de
License: MIT
Provides-Extra: tests
Provides-Extra: docs
License-File: LICENSE
